{
  "version": 1,
  "dataset": "realmedqa",
  "created_at": "2026-05-27T16:32:51.130235",
  "selection_strategy": "all",
  "subset_seed": 42,
  "requested_num_samples": 230,
  "available_question_count": 230,
  "selection_count": 230,
  "question_ids": [
    "realmedqa_3cc80612a61e",
    "realmedqa_e33b8d1da425",
    "realmedqa_c9f4e2226af2",
    "realmedqa_37ea72b15ff6",
    "realmedqa_ef56d53f750a",
    "realmedqa_a559ec1fd971",
    "realmedqa_476767e91f16",
    "realmedqa_50344cb196a1",
    "realmedqa_88cd78cbcf6e",
    "realmedqa_29e621695b3f",
    "realmedqa_caf06f6e635a",
    "realmedqa_6328b67806d1",
    "realmedqa_61b35ff82a31",
    "realmedqa_4e8962ebb9c6",
    "realmedqa_7a0df4bec2cf",
    "realmedqa_3895bc8334e7",
    "realmedqa_8f0c88ef7252",
    "realmedqa_03541d7b11c0",
    "realmedqa_fba122850d60",
    "realmedqa_41e31fc85c21",
    "realmedqa_935a47f34694",
    "realmedqa_181bbfc78877",
    "realmedqa_a1bc18dba5f4",
    "realmedqa_32244f1eb6e6",
    "realmedqa_f5355d859be7",
    "realmedqa_027942fe8f25",
    "realmedqa_5263eaa81c55",
    "realmedqa_69595782ba1a",
    "realmedqa_a0cca3d59bfb",
    "realmedqa_fb6f90d6f240",
    "realmedqa_fd65e595ab3c",
    "realmedqa_8b4e4029853b",
    "realmedqa_649717746554",
    "realmedqa_3e8a46a78711",
    "realmedqa_c3c2c2a01343",
    "realmedqa_deede847201d",
    "realmedqa_d2ed428f285a",
    "realmedqa_3d1fbb2352d1",
    "realmedqa_891c382117d6",
    "realmedqa_ac64e83bae17",
    "realmedqa_0073cbc35700",
    "realmedqa_2d4726127715",
    "realmedqa_611df9a75ba2",
    "realmedqa_8a315671c8f6",
    "realmedqa_7f7683c72a57",
    "realmedqa_cc6782804a45",
    "realmedqa_b119f9acc405",
    "realmedqa_ab2970ae08df",
    "realmedqa_fe095252e09f",
    "realmedqa_a42a44fde75b",
    "realmedqa_fef7d473adc5",
    "realmedqa_467ff81e0475",
    "realmedqa_913a92e432d0",
    "realmedqa_9fa07ebf6895",
    "realmedqa_20f9b4eacd93",
    "realmedqa_455575285529",
    "realmedqa_f22a924281fa",
    "realmedqa_a6e97ffd050c",
    "realmedqa_27cdf89c67a7",
    "realmedqa_ac38797c4668",
    "realmedqa_4a90603979bf",
    "realmedqa_7cc806f8c286",
    "realmedqa_002c645e2863",
    "realmedqa_1841b38793e5",
    "realmedqa_01cbbc335edf",
    "realmedqa_8fa613f109ec",
    "realmedqa_e8474b5a2341",
    "realmedqa_ad3ddf621073",
    "realmedqa_5eaa8da22160",
    "realmedqa_fb9e87199e1a",
    "realmedqa_162bb07eb130",
    "realmedqa_19c9a30d284b",
    "realmedqa_ad2b76eb96d2",
    "realmedqa_96e1713a543a",
    "realmedqa_d9fe98e0e327",
    "realmedqa_2360f70e02e1",
    "realmedqa_638847ddc50e",
    "realmedqa_5b39b21c4c81",
    "realmedqa_06f855b5abca",
    "realmedqa_0927626de213",
    "realmedqa_3b8ad30360e2",
    "realmedqa_16c7a9187cda",
    "realmedqa_63c41963d0f9",
    "realmedqa_c04db380fb49",
    "realmedqa_9a4a27ba2fc5",
    "realmedqa_a65aa564ce88",
    "realmedqa_8213cad73955",
    "realmedqa_7050dfc25a80",
    "realmedqa_0726c3a53f40",
    "realmedqa_4122091be205",
    "realmedqa_71c938867827",
    "realmedqa_bee7af71e697",
    "realmedqa_d9fd0dfdc6db",
    "realmedqa_c0e82f50eaf2",
    "realmedqa_3b54ac37a689",
    "realmedqa_99c8063cf3cf",
    "realmedqa_9a1ada6bc253",
    "realmedqa_197aed0bdb4b",
    "realmedqa_6cbc804be65a",
    "realmedqa_99ad8030606a",
    "realmedqa_b854d86411cd",
    "realmedqa_b6c51957e796",
    "realmedqa_3d835ccfb898",
    "realmedqa_ef920f279f42",
    "realmedqa_d24680320e1e",
    "realmedqa_fa0fe56de92e",
    "realmedqa_718cbd7b318c",
    "realmedqa_332d0c1960d1",
    "realmedqa_49d5fec8c4a7",
    "realmedqa_bf28796d8887",
    "realmedqa_0623d0e7dd38",
    "realmedqa_6383fecd98b4",
    "realmedqa_20575262955a",
    "realmedqa_9e955912fa23",
    "realmedqa_6bcdf7508e4e",
    "realmedqa_c2d52cfa44b0",
    "realmedqa_1904d9465519",
    "realmedqa_150b42eb7ab9",
    "realmedqa_b4be6cd0f028",
    "realmedqa_0e9472e530f5",
    "realmedqa_70eadc28dd68",
    "realmedqa_3cf0111d9ae0",
    "realmedqa_b545e9814ddb",
    "realmedqa_4cb39f3a548a",
    "realmedqa_bfba11cf2f61",
    "realmedqa_86af5f54984f",
    "realmedqa_9dcd75f89eff",
    "realmedqa_4639a4234d86",
    "realmedqa_7411c6047bd9",
    "realmedqa_2a335b5987e9",
    "realmedqa_899ca8996b55",
    "realmedqa_6437d625a749",
    "realmedqa_2429d99bddfa",
    "realmedqa_bb0692d7f6c8",
    "realmedqa_88f9c9696507",
    "realmedqa_cbede23dda15",
    "realmedqa_d4aa4ec1d6d2",
    "realmedqa_1182ccf22b1a",
    "realmedqa_0526b6fbf7ff",
    "realmedqa_8ec136728564",
    "realmedqa_741237883755",
    "realmedqa_5ac6c9849149",
    "realmedqa_7a744425a774",
    "realmedqa_d6c5b5140498",
    "realmedqa_eedcf766e908",
    "realmedqa_be6acc65c111",
    "realmedqa_39b899b28404",
    "realmedqa_9db691433254",
    "realmedqa_12eb44733e79",
    "realmedqa_cb3329282c05",
    "realmedqa_a7de55777b48",
    "realmedqa_508428e2a13b",
    "realmedqa_188cf8d87266",
    "realmedqa_67e235b0c9e0",
    "realmedqa_df018ca4c243",
    "realmedqa_9b7738326931",
    "realmedqa_ace2393242ba",
    "realmedqa_dfb218e86b0b",
    "realmedqa_f031d05d4199",
    "realmedqa_8ef4c38c4828",
    "realmedqa_cd19f4c1921a",
    "realmedqa_9772fd01958b",
    "realmedqa_859b8210d12d",
    "realmedqa_4251ac4a22b1",
    "realmedqa_bc06fe70fd57",
    "realmedqa_08d1f0e99bdd",
    "realmedqa_0443c07a89c2",
    "realmedqa_c410f1e2a056",
    "realmedqa_bb86827d38a0",
    "realmedqa_320a36b672ee",
    "realmedqa_5cd3b0615ac5",
    "realmedqa_cfec308a6a5e",
    "realmedqa_1823244730ff",
    "realmedqa_fe81d1d0eac4",
    "realmedqa_b6b249981a9a",
    "realmedqa_f85220238dd2",
    "realmedqa_a5248915e65f",
    "realmedqa_8d0dfc5fb0a3",
    "realmedqa_261d26d7f5e1",
    "realmedqa_35aafd0ebe08",
    "realmedqa_2c80b1920ff3",
    "realmedqa_d1610654eb3b",
    "realmedqa_e9d25abde157",
    "realmedqa_32cecdac9422",
    "realmedqa_77cdaa5a29cc",
    "realmedqa_f7e49b5771b8",
    "realmedqa_e17cfc7db5b5",
    "realmedqa_1d77ebc5779a",
    "realmedqa_7bfbba08dfa6",
    "realmedqa_090050c73537",
    "realmedqa_cb390ddd3bb1",
    "realmedqa_19a7c2c7bba4",
    "realmedqa_2f1a1cdf5b6e",
    "realmedqa_b56c6aa6ec63",
    "realmedqa_4e288a709d6b",
    "realmedqa_6fc6ef42e660",
    "realmedqa_e54c90c5ac22",
    "realmedqa_614f35c69882",
    "realmedqa_3c2e47e17a45",
    "realmedqa_e39ce81e458d",
    "realmedqa_48edf606141c",
    "realmedqa_55c1e4385af3",
    "realmedqa_3d8802b0372b",
    "realmedqa_d9ac486184d3",
    "realmedqa_3713baa88cea",
    "realmedqa_f37935b08781",
    "realmedqa_c5d3fc8caef0",
    "realmedqa_4648f3895f2d",
    "realmedqa_dd26b1eea8c9",
    "realmedqa_f0c8170c5813",
    "realmedqa_1322561be4ae",
    "realmedqa_07659bd8f08c",
    "realmedqa_88bec9e015e6",
    "realmedqa_b261ea64991b",
    "realmedqa_0418742d3801",
    "realmedqa_b860d46e011d",
    "realmedqa_e7cd91a87acb",
    "realmedqa_f5f67e43a234",
    "realmedqa_1e0cead437ab",
    "realmedqa_1417d8e29409",
    "realmedqa_e3711759e202",
    "realmedqa_60f4f0eae2da",
    "realmedqa_49f08af24528",
    "realmedqa_fd903400d1b9",
    "realmedqa_fea35f1ac070",
    "realmedqa_4e98f1814191",
    "realmedqa_a3a46a1cf029",
    "realmedqa_abfc74923349",
    "realmedqa_44d2313baacc",
    "realmedqa_0ed5e48d773e"
  ],
  "selection_key": "n230_seed42",
  "subset_hash": "d70e0169903b",
  "subset_tag": "n230_seed42_hd70e0169903b",
  "subset_id": "realmedqa__n230_seed42_hd70e0169903b"
}